llama_index/readers/twitter/__init__.py
llama_index/readers/twitter/base.py
llama_index_readers_twitter-0.4.1.dist-info/METADATA
llama_index_readers_twitter-0.4.1.dist-info/WHEEL
llama_index_readers_twitter-0.4.1.dist-info/licenses/LICENSE
llama_index_readers_twitter-0.4.1.dist-info/RECORD
