Metadata-Version: 2.4
Name: llama-index-readers-twitter
Version: 0.4.1
Summary: llama-index readers twitter integration
Author-email: Your Name <you@example.com>
Maintainer: ravi03071991
License-Expression: MIT
License-File: LICENSE
Requires-Python: <4.0,>=3.9
Requires-Dist: llama-index-core<0.15,>=0.13.0
Requires-Dist: tweepy<5,>=4.14.0
